strong_aws_pkg/__init__.py
strong_aws_pkg/json_extension.py
strong_aws_pkg/strong_aws_lambda.py
strong_aws_pkg/strong_contract_mapper.py
strong_aws_pkg/strong_custom_resource.py
strong_aws_pkg/strong_custom_resource_base_contracts.py
strong_aws_lambda.contract-0.2.2.dist-info/LICENSE
strong_aws_lambda.contract-0.2.2.dist-info/WHEEL
strong_aws_lambda.contract-0.2.2.dist-info/METADATA
strong_aws_lambda.contract-0.2.2.dist-info/RECORD
