Metadata-Version: 2.1
Name: strong-aws-lambda.contract
Version: 0.2.2
Summary: Extra lambda utils
License: MIT
Author: Rodrigo Farias Rezino
Author-email: rodrigofrezino@gmail.com
Requires-Python: >=3.6,<4.0
Classifier: License :: OSI Approved :: MIT License
Classifier: Programming Language :: Python :: 3
Classifier: Programming Language :: Python :: 3.6
Classifier: Programming Language :: Python :: 3.7
Provides-Extra: strong-aws-pkg
Provides-Extra: test
Requires-Dist: aws-lambda-context (>=1.1,<2.0)
Requires-Dist: dacite (>=1.0,<2.0)
